accounts/__init__.py
accounts/admin.py
accounts/context_processors.py
accounts/middleware.py
accounts/models.py
accounts/signals.py
accounts/urls.py
accounts/views.py
accounts/migrations/0001_initial.py
accounts/migrations/__init__.py
accounts/templatetags/__init__.py
accounts/templatetags/form_extras.py
accounts/tests/__init__.py
accounts/tests/test_middleware.py
accounts/tests/test_models.py
accounts/tests/test_urls.py
accounts/tests/test_views.py
django_users_plus-1.0.1.dist-info/DESCRIPTION.rst
django_users_plus-1.0.1.dist-info/METADATA
django_users_plus-1.0.1.dist-info/metadata.json
django_users_plus-1.0.1.dist-info/RECORD
django_users_plus-1.0.1.dist-info/top_level.txt
django_users_plus-1.0.1.dist-info/WHEEL
