Metadata-Version: 2.0
Name: django-users-plus
Version: 1.0.1
Summary: A django app that provides extra features including Masquerading, Local Timezone enablement, and extra fields to User model
Home-page: http://github.com/foundertherapy/django-users-plus/
Author: Dana Spiegel
Author-email: dana@foundertherapy.co
License: UNKNOWN
Download-URL: https://github.com/foundertherapy/django-users-plus/archive/1.0.1.tar.gz
Keywords: users,django,masquerading,masquerade,impersonate,timezone
Platform: UNKNOWN
Requires-Dist: Django (>=1.9)
Requires-Dist: django-timezone-field (>=1.1)
Requires-Dist: django-localflavor (==1.1)
